diebold_mariano_test/__init__.py
diebold_mariano_test/diebold_mariano_test.py
diebold_mariano_test/diebold_mariano_test_test.py
diebold_mariano_test-0.0.8.dist-info/LICENSE
diebold_mariano_test-0.0.8.dist-info/METADATA
diebold_mariano_test-0.0.8.dist-info/WHEEL
diebold_mariano_test-0.0.8.dist-info/top_level.txt
diebold_mariano_test-0.0.8.dist-info/RECORD
