Metadata-Version: 2.1
Name: diebold-mariano-test
Version: 0.0.8
Summary: Diebold Mariano test
Home-page: https://github.com/echosun1996/DieboldMarianoTest
Author: echosun
Author-email: echosun1996@126.com
License: UNKNOWN
Platform: UNKNOWN
Classifier: Programming Language :: Python :: 3
Classifier: Programming Language :: Python :: 3.5
Classifier: Programming Language :: Python :: 3.6
Classifier: Programming Language :: Python :: 3.7
Classifier: Programming Language :: Python :: 3.8
Classifier: License :: OSI Approved :: GNU General Public License v3 (GPLv3)
Classifier: Operating System :: OS Independent
Requires-Python: >=3.5
Requires-Dist: scipy (>=1.4.1)
